aleksis/apps/order/__init__.py
aleksis/apps/order/address_label.html
aleksis/apps/order/address_label_style.css
aleksis/apps/order/admin.py
aleksis/apps/order/apps.py
aleksis/apps/order/filters.py
aleksis/apps/order/forms.py
aleksis/apps/order/frontend/components/order_form/ControlRow.vue
aleksis/apps/order/frontend/components/order_form/CopyToClipboardButton.vue
aleksis/apps/order/frontend/components/order_form/DigitalProducts.vue
aleksis/apps/order/frontend/components/order_form/DigitalProductsByOrder.vue
aleksis/apps/order/frontend/components/order_form/DigitalProductsPerson.vue
aleksis/apps/order/frontend/components/order_form/MainContainer.vue
aleksis/apps/order/frontend/components/order_form/OptionRadio.vue
aleksis/apps/order/frontend/components/order_form/OptionRow.vue
aleksis/apps/order/frontend/components/order_form/OrderForm.graphql
aleksis/apps/order/frontend/components/order_form/OrderForm.vue
aleksis/apps/order/frontend/components/order_form/OrderItem.vue
aleksis/apps/order/frontend/components/order_form/TotalRow.vue
aleksis/apps/order/frontend/components/order_form/createShareMutation.graphql
aleksis/apps/order/frontend/components/order_form/digitalProducts.graphql
aleksis/apps/order/frontend/components/order_form/digitalProductsPerson.graphql
aleksis/apps/order/frontend/components/order_form/orderMutation.graphql
aleksis/apps/order/frontend/components/order_form/util.js
aleksis/apps/order/frontend/components/order_form/whoAmI.graphql
aleksis/apps/order/frontend/index.js
aleksis/apps/order/frontend/messages/de.json
aleksis/apps/order/frontend/messages/en.json
aleksis/apps/order/locale/.keepdir
aleksis/apps/order/locale/ar/LC_MESSAGES/django.mo
aleksis/apps/order/locale/ar/LC_MESSAGES/django.po
aleksis/apps/order/locale/de_DE/LC_MESSAGES/django.mo
aleksis/apps/order/locale/de_DE/LC_MESSAGES/django.po
aleksis/apps/order/locale/fr/LC_MESSAGES/django.mo
aleksis/apps/order/locale/fr/LC_MESSAGES/django.po
aleksis/apps/order/locale/la/LC_MESSAGES/django.mo
aleksis_app_order-0.6.dist-info/METADATA
aleksis_app_order-0.6.dist-info/WHEEL
aleksis_app_order-0.6.dist-info/entry_points.txt
aleksis_app_order-0.6.dist-info/RECORD
