Metadata-Version: 2.1
Name: aleksis-app-order
Version: 0.6
Summary: AlekSIS (School Information System) — App Order (Manage orders)
Home-page: https://edugit.org/hansegucker/AlekSIS-App-Order
License: EUPL-1.2
Author: Jonathan Weth
Author-email: dev@jonathanweth.de
Maintainer: Jonathan Weth
Maintainer-email: dev@jonathanweth.de
Requires-Python: >=3.9,<4.0
Classifier: Environment :: Web Environment
Classifier: Intended Audience :: Education
Classifier: License :: OSI Approved :: European Union Public Licence 1.2 (EUPL 1.2)
Classifier: Programming Language :: Python :: 3
Classifier: Programming Language :: Python :: 3.9
Classifier: Programming Language :: Python :: 3.10
Classifier: Programming Language :: Python :: 3.11
Classifier: Topic :: Education
Requires-Dist: aleksis-core (>=3.0,<4.0)
Requires-Dist: blabel (>=0.1.4,<0.2.0)
Requires-Dist: defusedxml (>=0.7.1,<0.8.0)
Requires-Dist: html2text (>=2020.1.16,<2021.0.0)
Project-URL: Repository, https://edugit.org/hansegucker/AlekSIS-App-Order
